[
    {
        "id": "03e91b91ae2dd78a",
        "type": "tab",
        "label": "actionserver_icon",
        "disabled": false,
        "info": ""
    },
    {
        "id": "3e9e6445909ff09c",
        "type": "http request",
        "z": "03e91b91ae2dd78a",
        "name": "",
        "method": "GET",
        "ret": "obj",
        "paytoqs": "ignore",
        "url": "",
        "tls": "",
        "persist": false,
        "proxy": "",
        "authType": "",
        "senderr": false,
        "x": 310,
        "y": 120,
        "wires": [
            [
                "56cf445d89e1b585"
            ]
        ]
    },
    {
        "id": "2304de4f305ac5e2",
        "type": "template",
        "z": "03e91b91ae2dd78a",
        "name": "",
        "field": "url",
        "fieldType": "msg",
        "format": "handlebars",
        "syntax": "mustache",
        "template": "https://api.openweathermap.org/data/2.5/weather?q={{slots.location}}&appid=API-KEY HERE&units=metric",
        "output": "str",
        "x": 140,
        "y": 120,
        "wires": [
            [
                "3e9e6445909ff09c"
            ]
        ]
    },
    {
        "id": "cdde7f153cc85061",
        "type": "template",
        "z": "03e91b91ae2dd78a",
        "name": "",
        "field": "payload.text",
        "fieldType": "msg",
        "format": "handlebars",
        "syntax": "mustache",
        "template": "It is {{payload.weather.0.description}} in {{payload.name}}, {{payload.sys.country}} at the moment. The temperature is {{payload.main.temp}} degrees, the humidity is {{payload.main.humidity}}% and the wind speed is {{payload.wind.speed}} m/s.",
        "output": "str",
        "x": 640,
        "y": 120,
        "wires": [
            [
                "509b633bdffb9c0e"
            ]
        ]
    },
    {
        "id": "5a3b67207b4f8d4a",
        "type": "http in",
        "z": "03e91b91ae2dd78a",
        "name": "",
        "url": "/actionserver",
        "method": "post",
        "upload": false,
        "swaggerDoc": "",
        "x": 90,
        "y": 40,
        "wires": [
            [
                "57cb1291aaeb2d57"
            ]
        ]
    },
    {
        "id": "14ef588d4a65fd43",
        "type": "http response",
        "z": "03e91b91ae2dd78a",
        "name": "",
        "statusCode": "",
        "headers": {},
        "x": 650,
        "y": 200,
        "wires": []
    },
    {
        "id": "57cb1291aaeb2d57",
        "type": "init",
        "z": "03e91b91ae2dd78a",
        "name": "",
        "x": 270,
        "y": 40,
        "wires": [
            [
                "2304de4f305ac5e2"
            ]
        ]
    },
    {
        "id": "afdff720c12f09b4",
        "type": "finish",
        "z": "03e91b91ae2dd78a",
        "name": "",
        "x": 490,
        "y": 200,
        "wires": [
            [
                "14ef588d4a65fd43"
            ]
        ]
    },
    {
        "id": "509b633bdffb9c0e",
        "type": "sendextra",
        "z": "03e91b91ae2dd78a",
        "name": "",
        "position": "",
        "positionType": "num",
        "text": "payload.text",
        "textType": "msg",
        "image": "payload.image",
        "imageType": "msg",
        "attachment": "",
        "attachmentType": "str",
        "senderr": false,
        "x": 340,
        "y": 200,
        "wires": [
            [
                "afdff720c12f09b4"
            ]
        ]
    },
    {
        "id": "56cf445d89e1b585",
        "type": "template",
        "z": "03e91b91ae2dd78a",
        "name": "",
        "field": "payload.image",
        "fieldType": "msg",
        "format": "handlebars",
        "syntax": "mustache",
        "template": "https://openweathermap.org/img/wn/{{payload.weather.0.icon}}@2x.png",
        "output": "str",
        "x": 480,
        "y": 120,
        "wires": [
            [
                "cdde7f153cc85061"
            ]
        ]
    }
]